pysquril/__init__.py
pysquril/backends.py
pysquril/exc.py
pysquril/generator.py
pysquril/interactive.py
pysquril/parser.py
pysquril/test_data.py
pysquril/tests.py
pysquril/utils.py
pysquril-1.0.4.dist-info/METADATA
pysquril-1.0.4.dist-info/WHEEL
pysquril-1.0.4.dist-info/RECORD
