Metadata-Version: 2.1
Name: pysquril
Version: 1.0.4
Summary: Python implementation of structured URI query language
Home-page: https://github.com/unioslo/pysquril
Author: Leon du Toit
Author-email: l.c.d.toit@usit.uio.no
Requires-Python: >=3.9,<4.0
Classifier: Programming Language :: Python :: 3
Classifier: Programming Language :: Python :: 3.9
Classifier: Programming Language :: Python :: 3.10
Classifier: Programming Language :: Python :: 3.11
Classifier: Programming Language :: Python :: 3.12
Classifier: Programming Language :: Python :: 3.13
Requires-Dist: psycopg2 (>=2.9.3)
Project-URL: Repository, https://github.com/unioslo/pysquril
